Workbook

Sheet Gestion globale
A1: Date | B1: Personne | C1: Type (Achat/Vente/Dépense) | D1: Description | E1: Lot | F1: Montant (MAD) | G1: Mode de paiement | H1: Remarque | I1: Statut du lot | J1: Quantité (pièces)
B2: ADAM | C2: ACHAT | E2: LOT 1 | F2: 18500 | J2: 1
B3: ABDELGHAFOUR | C3: ACHAT | E3: LOT 1 | F3: 20000 | J3: 1
B4: ADAM | C4: ACHAT | E4: LOT 2 | F4: 2500 | J4: 1
B5: ABDELGHAFOUR | C5: ACHAT | E5: LOT 2 | F5: 2500 | J5: 1
B6: ADAM | C6: VENTE | D6: FAS | E6: LOT 1 | F6: 7800 | J6: 1
B7: ADAM | C7: VENTE | D7: NSSIB MBAR | E7: LOT 2 | F7: 1800 | J7: 1
B8: ADAM | C8: ACHAT | E8: LOT 3 | F8: 4000 | J8: 1
B9: ABDELGHAFOUR | C9: ACHAT | E9: LOT 3 | F9: 5000 | J9: 1
B10: ABDELGHAFOUR | C10: ACHAT | E10: LOT JAG | F10: 4200 | J10: 1
B11: ADAM | C11: ACHAT | E11: LOT JAG | F11: 1600 | J11: 1
B12: ABDELGHAFOUR | C12: VENTE | D12: CATA | E12: LOT JAG | F12: 3200 | J12: 1
B13: ABDELGHAFOUR | C13: ACHAT | E13: LOT ALL | F13: 5000 | J13: 1
B14: ADAM | C14: ACHAT | E14: LOT ALL | F14: 7000 | J14: 1
B15: ADAM | C15: VENTE | D15: TOURSADE | E15: LOT ALL | F15: 2300 | J15: 1
B16: ADAM | C16: VENTE | D16: DENUD | E16: LOT ALL | F16: 3300 | J16: 1
B17: ABDELGHAFOUR | C17: ACHAT | D17: AYOUB PAYE | E17: LOT FRIGO | F17: 25000 | J17: 1
B18: ABDELGHAFOUR | C18: VENTE | D18: BARAKA | E18: LOT FRIGO | F18: 7000 | J18: 1
B19: ADAM | C19: VENTE | D19: CRIQ | E19: LOT FRIGO | F19: 1700 | J19: 1
B20: ADAM | C20: ACHAT | D20: DEPENSE | E20: LOT FRIGO | F20: 1800 | J20: 1
B21: ABDELGHAFOUR | C21: ACHAT | D21: 2 GEAR | E21: LOT GEAR | F21: 3100 | J21: 1
B22: ABDELGHAFOUR | C22: ACHAT | E22: LOT CLARK | F22: 5000 | J22: 1
B23: ADAM | C23: ACHAT | E23: LOT CLARK | F23: 12000 | J23: 1
B24: ABDELGHAFOUR | C24: ACHAT | D24: avance | E24: lot 928 | F24: 1500 | J24: 1
B25: ABDELGHAFOUR | C25: ACHAT | D25: GRUE | E25: lot 928 | F25: 2000 | J25: 1
B26: ABDELGHAFOUR | C26: ACHAT | D26: REMORQUE | E26: lot 928 | F26: 8000 | J26: 1
B27: dad | C27: ACHAT | D27: 3m | E27: lot 928 | F27: 30000 | J27: 1
B28: ABDELGHAFOUR | C28: ACHAT | D28: WAFACASH | E28: lot 928 | F28: 5000 | J28: 1
B29: ABDELGHAFOUR | C29: ACHAT | D29: 3M | E29: lot ass | F29: 30000 | J29: 1
B30: AHMED | C30: ACHAT | D30: 4 ET 5000 AV | E30: lot ass | F30: 45000 | J30: 1
B31: ADAM | C31: ACHAT | D31: TRASN | E31: lot ass | F31: 1000 | J31: 1
B32: ADAM | C32: VENTE | D32: TRAFIC | E32: lot ass | F32: 1000 | J32: 1
B33: AHMED | C33: VENTE | D33: ASIA | E33: lot ass | F33: 50000 | J33: 1
B34: ABDELGHAFOUR | C34: VENTE | D34: TRAFIC | E34: lot ass | F34: 8000 | J34: 1
B35: ABDELGHAFOUR | C35: VENTE | D35: r4 | E35: lot ass | F35: 7000 | J35: 1
B36: ABDELGHAFOUR | C36: VENTE | D36: KANGOO | E36: LOT ASS | F36: 20000 | J36: 1

Sheet Résumé automatique
A1: Personne | B1: Total Achats | C1: Total Ventes | D1: Total Dépenses | E1: Résultat
A2: Abdelghafour | B2: =SUMIFS('Gestion globale'!F:F,'Gestion globale'!B:B,"Abdelghafour",'Gestion globale'!C:C,"Achat") | C2: =SUMIFS('Gestion globale'!F:F,'Gestion globale'!B:B,"Abdelghafour",'Gestion globale'!C:C,"Vente") | D2: =SUMIFS('Gestion globale'!F:F,'Gestion globale'!B:B,"Abdelghafour",'Gestion globale'!C:C,"Dépense") | E2: =C2-B2-D2
A3: Adam | B3: =SUMIFS('Gestion globale'!F:F,'Gestion globale'!B:B,"Adam",'Gestion globale'!C:C,"Achat") | C3: =SUMIFS('Gestion globale'!F:F,'Gestion globale'!B:B,"Adam",'Gestion globale'!C:C,"Vente") | D3: =SUMIFS('Gestion globale'!F:F,'Gestion globale'!B:B,"Adam",'Gestion globale'!C:C,"Dépense") | E3: =C3-B3-D3

Sheet Suivi par lot
A1: Lot | B1: Total Achats | C1: Total Ventes | D1: Total Dépenses | E1: Résultat
A2: Lot 1 COM | B2: =SUMIFS('Gestion globale'!F:F,'Gestion globale'!E:E,"Lot 1",'Gestion globale'!C:C,"Achat") | C2: 7800 | E2: =C2-B2-D2
A3: Lot 2 BAW | B3: =SUMIFS('Gestion globale'!F:F,'Gestion globale'!E:E,"Lot 2",'Gestion globale'!C:C,"Achat") | C3: =SUMIFS('Gestion globale'!F:F,'Gestion globale'!E:E,"Lot 2",'Gestion globale'!C:C,"Vente") | D3: =SUMIFS('Gestion globale'!F:F,'Gestion globale'!E:E,"Lot 2",'Gestion globale'!C:C,"Dépense") | E3: =C3-B3-D3
A4: Lot 3 INST | B4: =SUMIFS('Gestion globale'!F:F,'Gestion globale'!E:E,"Lot 3",'Gestion globale'!C:C,"Achat") | C4: =SUMIFS('Gestion globale'!F:F,'Gestion globale'!E:E,"Lot 3",'Gestion globale'!C:C,"Vente") | D4: =SUMIFS('Gestion globale'!F:F,'Gestion globale'!E:E,"Lot 3",'Gestion globale'!C:C,"Dépense") | E4: =C4-B4-D4
A5: Lot ALL | B5: =SUMIFS('Gestion globale'!F:F,'Gestion globale'!E:E,"Lot ALL",'Gestion globale'!C:C,"Achat") | C5: =SUMIFS('Gestion globale'!F:F,'Gestion globale'!E:E,"Lot ALL",'Gestion globale'!C:C,"Vente") | D5: =SUMIFS('Gestion globale'!F:F,'Gestion globale'!E:E,"Lot ALL",'Gestion globale'!C:C,"Dépense") | E5: =C5-B5-D5
A6: LOT JAG | B6: =SUMIFS('Gestion globale'!F:F,'Gestion globale'!E:E,"Lot JAG",'Gestion globale'!C:C,"Achat") | C6: =SUMIFS('Gestion globale'!F:F,'Gestion globale'!E:E,"Lot JAG",'Gestion globale'!C:C,"Vente") | D6: =SUMIFS('Gestion globale'!F:F,'Gestion globale'!E:E,"Lot JAG",'Gestion globale'!C:C,"Dépense") | E6: =C6-B6-D6
A7: Lot FRIGO | B7: =SUMIFS('Gestion globale'!F:F,'Gestion globale'!E:E,"Lot FRIGO",'Gestion globale'!C:C,"Achat") | C7: =SUMIFS('Gestion globale'!F:F,'Gestion globale'!E:E,"Lot FRIGO",'Gestion globale'!C:C,"Vente") | D7: =SUMIFS('Gestion globale'!F:F,'Gestion globale'!E:E,"Lot FRIGO",'Gestion globale'!C:C,"Dépense") | E7: =C7-B7-D7
A8: Lot GEAR | B8: =SUMIFS('Gestion globale'!F:F,'Gestion globale'!E:E,"Lot GEAR",'Gestion globale'!C:C,"Achat") | C8: =SUMIFS('Gestion globale'!F:F,'Gestion globale'!E:E,"Lot GEAR",'Gestion globale'!C:C,"Vente") | D8: =SUMIFS('Gestion globale'!F:F,'Gestion globale'!E:E,"Lot GEAR",'Gestion globale'!C:C,"Dépense") | E8: =C8-B8-D8
A9: Lot CLARK | B9: =SUMIFS('Gestion globale'!F:F,'Gestion globale'!E:E,"Lot CLARK",'Gestion globale'!C:C,"Achat") | C9: =SUMIFS('Gestion globale'!F:F,'Gestion globale'!E:E,"Lot 3",'Gestion globale'!C:C,"Vente") | D9: =SUMIFS('Gestion globale'!F:F,'Gestion globale'!E:E,"Lot 3",'Gestion globale'!C:C,"Dépense") | E9: =C9-B9-D9
A10: Lot 928 | B10: =SUMIFS('Gestion globale'!F:F,'Gestion globale'!E:E,"Lot 928",'Gestion globale'!C:C,"Achat") | C10: =SUMIFS('Gestion globale'!F:F,'Gestion globale'!E:E,"Lot 3",'Gestion globale'!C:C,"Vente") | D10: =SUMIFS('Gestion globale'!F:F,'Gestion globale'!E:E,"Lot 3",'Gestion globale'!C:C,"Dépense") | E10: =C10-B10-D10
A11: Lot ASS | B11: =SUMIFS('Gestion globale'!F:F,'Gestion globale'!E:E,"Lot ASS",'Gestion globale'!C:C,"Achat") | C11: =SUMIFS('Gestion globale'!F:F,'Gestion globale'!E:E,"Lot ASS",'Gestion globale'!C:C,"Vente") | D11: =SUMIFS('Gestion globale'!F:F,'Gestion globale'!E:E,"Lot ASS",'Gestion globale'!C:C,"Dépense") | E11: =C11-B11-D11
A12: Lot 11 | B12: =SUMIFS('Gestion globale'!F:F,'Gestion globale'!E:E,"Lot 11",'Gestion globale'!C:C,"Achat") | C12: =SUMIFS('Gestion globale'!F:F,'Gestion globale'!E:E,"Lot 11",'Gestion globale'!C:C,"Vente") | D12: =SUMIFS('Gestion globale'!F:F,'Gestion globale'!E:E,"Lot 11",'Gestion globale'!C:C,"Dépense") | E12: =C12-B12-D12
A13: Lot 12 | B13: =SUMIFS('Gestion globale'!F:F,'Gestion globale'!E:E,"Lot 12",'Gestion globale'!C:C,"Achat") | C13: =SUMIFS('Gestion globale'!F:F,'Gestion globale'!E:E,"Lot 12",'Gestion globale'!C:C,"Vente") | D13: =SUMIFS('Gestion globale'!F:F,'Gestion globale'!E:E,"Lot 12",'Gestion globale'!C:C,"Dépense") | E13: =C13-B13-D13
A14: Lot 13 | B14: =SUMIFS('Gestion globale'!F:F,'Gestion globale'!E:E,"Lot 13",'Gestion globale'!C:C,"Achat") | C14: =SUMIFS('Gestion globale'!F:F,'Gestion globale'!E:E,"Lot 13",'Gestion globale'!C:C,"Vente") | D14: =SUMIFS('Gestion globale'!F:F,'Gestion globale'!E:E,"Lot 13",'Gestion globale'!C:C,"Dépense") | E14: =C14-B14-D14
A15: Lot 14 | B15: =SUMIFS('Gestion globale'!F:F,'Gestion globale'!E:E,"Lot 14",'Gestion globale'!C:C,"Achat") | C15: =SUMIFS('Gestion globale'!F:F,'Gestion globale'!E:E,"Lot 14",'Gestion globale'!C:C,"Vente") | D15: =SUMIFS('Gestion globale'!F:F,'Gestion globale'!E:E,"Lot 14",'Gestion globale'!C:C,"Dépense") | E15: =C15-B15-D15
A16: Lot 15 | B16: =SUMIFS('Gestion globale'!F:F,'Gestion globale'!E:E,"Lot 15",'Gestion globale'!C:C,"Achat") | C16: =SUMIFS('Gestion globale'!F:F,'Gestion globale'!E:E,"Lot 15",'Gestion globale'!C:C,"Vente") | D16: =SUMIFS('Gestion globale'!F:F,'Gestion globale'!E:E,"Lot 15",'Gestion globale'!C:C,"Dépense") | E16: =C16-B16-D16
A17: Lot 16 | B17: =SUMIFS('Gestion globale'!F:F,'Gestion globale'!E:E,"Lot 16",'Gestion globale'!C:C,"Achat") | C17: =SUMIFS('Gestion globale'!F:F,'Gestion globale'!E:E,"Lot 16",'Gestion globale'!C:C,"Vente") | D17: =SUMIFS('Gestion globale'!F:F,'Gestion globale'!E:E,"Lot 16",'Gestion globale'!C:C,"Dépense") | E17: =C17-B17-D17
A18: Lot 17 | B18: =SUMIFS('Gestion globale'!F:F,'Gestion globale'!E:E,"Lot 17",'Gestion globale'!C:C,"Achat") | C18: =SUMIFS('Gestion globale'!F:F,'Gestion globale'!E:E,"Lot 17",'Gestion globale'!C:C,"Vente") | D18: =SUMIFS('Gestion globale'!F:F,'Gestion globale'!E:E,"Lot 17",'Gestion globale'!C:C,"Dépense") | E18: =C18-B18-D18
A19: Lot 18 | B19: =SUMIFS('Gestion globale'!F:F,'Gestion globale'!E:E,"Lot 18",'Gestion globale'!C:C,"Achat") | C19: =SUMIFS('Gestion globale'!F:F,'Gestion globale'!E:E,"Lot 18",'Gestion globale'!C:C,"Vente") | D19: =SUMIFS('Gestion globale'!F:F,'Gestion globale'!E:E,"Lot 18",'Gestion globale'!C:C,"Dépense") | E19: =C19-B19-D19

Sheet Gestion des lots
A1: Lot | B1: Statut (OUVERT / FERMÉ) | C1: Remarque
A2: LOT 1

Sheet Suivi des avances
A1: Lot | B1: Personne | C1: Total Avancé (Achats + Dépenses) | D1: Total Encaissé (Ventes) | E1: Solde (À récupérer / À payer)
A2: 2026 – LOT FRIGO | B2: Abdelghafour | C2: =SUMIFS('Gestion globale'!F:F,'Gestion globale'!E:E,"LOT FRIGO",'Gestion globale'!B:B,"Abdelghafour",'Gestion globale'!C:C,"Achat")+SUMIFS('Gestion globale'!F:F,'Gestion globale'!E:E,"2026 – Remorque frigo – Thermo King",'Gestion globale'!B:B,"Abdelghafour",'Gestion globale'!C:C,"Dépense") | D2: =SUMIFS('Gestion globale'!F:F,'Gestion globale'!E:E,"lot frigo",'Gestion globale'!B:B,"Abdelghafour",'Gestion globale'!C:C,"Vente") | E2: =D2-C2
A3: 2026 – LOT FRIGO | B3: Adam | C3: =SUMIFS('Gestion globale'!F:F,'Gestion globale'!E:E,"LOT FRIGO",'Gestion globale'!B:B,"Adam",'Gestion globale'!C:C,"Achat")+SUMIFS('Gestion globale'!F:F,'Gestion globale'!E:E,"2026 – Remorque frigo – Thermo King",'Gestion globale'!B:B,"Abdelghafour",'Gestion globale'!C:C,"Dépense") | D3: =SUMIFS('Gestion globale'!F:F,'Gestion globale'!E:E,"LOT FRIGO",'Gestion globale'!B:B,"Adam",'Gestion globale'!C:C,"Vente") | E3: =D3-C3
